[{"reg_date":"2\/6\/2558","financial":[{"year":"2561","income":11483981.5800000001},{"year":"2560","income":2088610.3999999999},{"year":"2559","income":0},{"year":"2558","income":0}],"value_share":619254,"count_shareholder":5000,"company_shareholder":[{"Lastname":"ภูแก้ว","value_share":619254,"pct_share":10,"Firstname":"ธนินท์ทัศน์","count_share":5000,"Nationality":"TH"},{"Lastname":"ขุนทอง","value_share":4954033,"pct_share":80,"Firstname":"สุจรรยา","count_share":40000,"Nationality":"TH"},{"Lastname":"ภูแก้ว","value_share":619254,"pct_share":10,"Firstname":"พิเชษฐ์","count_share":5000,"Nationality":"TH","person":{"Number":5,"Title":"นาย","Name":"พิเชษฐ์ ภูแก้ว","PartyName":"รวมไทยสร้างชาติ","MpType":"แบ่งเขต","Id":"3233","IsMp":true,"IsActive":true,"IsSanator":false,"IsCabinet":false,"IsPmCandidate":false,"MpProvince":"สุรินทร์","MpZone":2,"MpList":"","Images":"\/yourcandidates\/candidates\/รวมไทยสร้างชาติ\/พิเชษฐ์-ภูแก้ว.webp","Party":{"Name":"รวมไทยสร้างชาติ","Color":"#1445C3","PartyType":"พรรค","IsActive":true,"Id":37,"Images":"https:\/\/sheets.wevis.info\/download\/noco\/They-Work-For-Us\/Parties\/Images\/71TBXfLKWiUR__KqSa.png"},"companyType":[],"totalValueShare":0,"countCompShare":0,"countDirector":0,"totalPctShare":0}}],"pct_share":10,"company_name_th":"ภูทองคำ จำกัด","company_id":"0325558000454","obj_tname":"การก่อสร้างอาคารที่ไม่ใช่ที่พักอาศัย","company_name_en":"PHUTHONGKHUM  CO., LTD","tsic":41002,"cap_amt":5000000,"company_value":6192541,"company_type_th":"บริษัทจำกัด","submit_obj_big_type":"F","full_address":"62 หมู่ที่ 16 ต.สลักได อ.เมืองสุรินทร์ จ.สุรินทร์","gov_fund_proj":null},{"reg_date":"09\/09\/2559","financial":[{"year":"2564","income":0},{"year":"2563","income":0},{"year":"2562","income":0},{"year":"2561","income":0}],"value_share":0,"count_shareholder":20000,"company_shareholder":[{"Lastname":"เป้ามงคล","value_share":0,"pct_share":30,"Firstname":"จำลอง","count_share":15000,"Nationality":"TH"},{"Lastname":"ภูแก้ว","value_share":0,"pct_share":40,"Firstname":"พิเชษฐ์","count_share":20000,"Nationality":"TH","person":{"Number":5,"Title":"นาย","Name":"พิเชษฐ์ ภูแก้ว","PartyName":"รวมไทยสร้างชาติ","MpType":"แบ่งเขต","Id":"3233","IsMp":true,"IsActive":true,"IsSanator":false,"IsCabinet":false,"IsPmCandidate":false,"MpProvince":"สุรินทร์","MpZone":2,"MpList":"","Images":"\/yourcandidates\/candidates\/รวมไทยสร้างชาติ\/พิเชษฐ์-ภูแก้ว.webp","Party":{"Name":"รวมไทยสร้างชาติ","Color":"#1445C3","PartyType":"พรรค","IsActive":true,"Id":37,"Images":"https:\/\/sheets.wevis.info\/download\/noco\/They-Work-For-Us\/Parties\/Images\/71TBXfLKWiUR__KqSa.png"},"companyType":[],"totalValueShare":0,"countCompShare":0,"countDirector":0,"totalPctShare":0}},{"Lastname":"เพิ่มพูนสินทรัพย์","value_share":0,"pct_share":30,"Firstname":"อำนาจ","count_share":15000,"Nationality":"TH"}],"pct_share":40,"company_name_th":"สุพรรณรินทร์ จำกัด","company_id":"0325559000831","obj_tname":"-","company_name_en":"SUPANRIN COMPANY LIMITED","tsic":41002,"cap_amt":5000000,"company_value":0,"company_type_th":"บริษัทจำกัด","submit_obj_big_type":"F","full_address":"62 หมู่ที่ 16  ต.สลักได อ.เมืองสุรินทร์ จ.สุรินทร์","gov_fund_proj":null},{"reg_date":"6\/12\/2561","financial":[{"year":"2565","income":0},{"year":"2564","income":0},{"year":"2563","income":0},{"year":"2562","income":0}],"value_share":0,"count_shareholder":15000,"company_shareholder":[{"Lastname":"ปรางทอง","value_share":0,"pct_share":40,"Firstname":"ภูมิพัฒน์","count_share":20000,"Nationality":"TH"},{"Lastname":"ลาภจิตรา","value_share":0,"pct_share":30,"Firstname":"จรูญ","count_share":15000,"Nationality":"TH"},{"Lastname":"ภูแก้ว","value_share":0,"pct_share":30,"Firstname":"พิเชษฐ์","count_share":15000,"Nationality":"TH","person":{"Number":5,"Title":"นาย","Name":"พิเชษฐ์ ภูแก้ว","PartyName":"รวมไทยสร้างชาติ","MpType":"แบ่งเขต","Id":"3233","IsMp":true,"IsActive":true,"IsSanator":false,"IsCabinet":false,"IsPmCandidate":false,"MpProvince":"สุรินทร์","MpZone":2,"MpList":"","Images":"\/yourcandidates\/candidates\/รวมไทยสร้างชาติ\/พิเชษฐ์-ภูแก้ว.webp","Party":{"Name":"รวมไทยสร้างชาติ","Color":"#1445C3","PartyType":"พรรค","IsActive":true,"Id":37,"Images":"https:\/\/sheets.wevis.info\/download\/noco\/They-Work-For-Us\/Parties\/Images\/71TBXfLKWiUR__KqSa.png"},"companyType":[],"totalValueShare":0,"countCompShare":0,"countDirector":0,"totalPctShare":0}}],"pct_share":30,"company_name_th":"พีพีเจ อิมปอร์ต เอ็กซ์ปอร์ต จำกัด","company_id":"0325561001288","obj_tname":"การขายส่งวัตถุดิบทางการเกษตรและสัตว์มีชีวิตโดยได้รับค่าตอบแทนหรือตามสัญญาจ้าง","company_name_en":"PPJ IMPORT EXPORT COMPANY LIMITED","tsic":46101,"cap_amt":5000000,"company_value":0,"company_type_th":"บริษัทจำกัด","submit_obj_big_type":"G","full_address":"62 หมู่ที่ 16 ต.สลักได อ.เมืองสุรินทร์ จ.สุรินทร์","gov_fund_proj":null}]