[{"full_address":"25  ถนนประชาธิปัตย์ ต.เบตง อ.เบตง จ.ยะลา","financial":[{"year":"2564","income":1200},{"year":"2563","income":0},{"year":"2562","income":0},{"year":"2561","income":0}],"value_share":248043,"submit_obj_big_type":"N","company_name_th":"รักษาความปลอดภัย บอส เอส กรุ๊ป จำกัด","pct_share":50,"obj_tname":"กิจกรรมการรักษาความปลอดภัยส่วนบุคคล","company_id":"0955564000619","reg_date":"23\/08\/2564","company_name_en":"BOSS S GROUP SECURITY GUARD CO., LTD.","tsic":80100,"cap_amt":2000000,"company_value":496085,"company_type_th":"บริษัทจำกัด","company_shareholder":[{"Lastname":"พยัฆพันธ์","value_share":99217,"Nationality":"TH","pct_share":20,"count_share":4000,"Firstname":"เพชรไพลิน"},{"Lastname":"พิณนุรัต","value_share":49609,"Nationality":"TH","pct_share":10,"count_share":2000,"Firstname":"พรชัย"},{"Lastname":"อิมัม","value_share":248043,"Nationality":"TH","pct_share":50,"count_share":10000,"Firstname":"อารยะ","person":{"Number":"","Title":"นาย","Name":"อารยะ อิมัม","PartyName":"ประชาชาติ","MpType":"บัญชีรายชื่อ","Id":"319","IsMp":true,"IsActive":true,"IsSanator":false,"IsCabinet":false,"IsPmCandidate":false,"MpProvince":"","MpZone":"","MpList":"","Images":"","Party":{"Name":"ประชาชาติ","Color":"#A56F05","PartyType":"พรรค","IsActive":true,"Id":9,"Images":"https:\/\/sheets.wevis.info\/download\/noco\/They-Work-For-Us\/Parties\/Images\/ประชาชาติ.jpg"},"companyType":[]}},{"Lastname":"อิมัม","value_share":99217,"Nationality":"TH","pct_share":20,"count_share":4000,"Firstname":"ฟารีดา"}],"count_shareholder":10000,"gov_fund_proj":null}]