{"People": [{"Name": "ประจิน นุ่มกัน", "Birthdate": "2005-10-07", "Number": 1, "Education": "ปริญญาเอก", "ExOccupation": "อาจารย์ประจำมหาวิทยาลัย", "Party": "รักษ์ผืนป่าประเทศไทย", "Province": "อุดรธานี", "Zone": 8, "Image": "", "PastGovernment": false, "PastOpposition": true}, {"Name": "อนุพงษ์ เผ่าจินดา", "Birthdate": "1979-10-13", "Number": 2, "Education": "ปริญญาเอก", "ExOccupation": "นักออกแบบท่าเต้น", "Party": "ทางเลือกใหม่", "Province": "อุดรธานี", "Zone": 8, "Image": "", "PastGovernment": false, "PastOpposition": true}, {"Name": "ปิยนาฎ แต้กุล", "Birthdate": "2006-11-12", "Number": 3, "Education": "ปริญญาโท", "ExOccupation": "เลขานุการนายกเทศมนตรี", "Party": "พลังปวงชนไทย", "Province": "อุดรธานี", "Zone": 8, "Image": "", "PastGovernment": false, "PastOpposition": true}, {"Name": "ภูมิศิษฏ์ คงมี", "Birthdate": "1978-06-05", "Number": 4, "Education": "อิฟลู", "ExOccupation": "สมาชิกสภากรุงเทพมหานคร", "Party": "ภูมิใจไทย", "Province": "อุดรธานี", "Zone": 8, "Image": "", "PastGovernment": false, "PastOpposition": true}, {"Name": "จุรินทร์ ลักษณวิศิษฏ์", "Birthdate": "2003-05-25", "Number": 5, "Education": "อิฟลู", "ExOccupation": "รับราชการครู", "Party": "พลังสังคม", "Province": "อุดรธานี", "Zone": 8, "Image": "", "PastGovernment": false, "PastOpposition": true}, {"Name": "ธนะสิทธิ์ โควสุรัตน์", "Birthdate": "1982-10-28", "Number": 6, "Education": "ด้อกเต้อ", "ExOccupation": "ผู้บริหารโรงเรียน", "Party": "รวมพลัง", "Province": "อุดรธานี", "Zone": 8, "Image": "https://sheets.wevis.info/download/noco/They-Work-For-Us/People/Images/%E0%B8%90%E0%B8%99%E0%B8%A0%E0%B8%B1%E0%B8%97%E0%B8%A3-%E0%B8%81%E0%B8%B4%E0%B8%95%E0%B8%95%E0%B8%B4%E0%B8%A7%E0%B8%87%E0%B8%A8%E0%B8%B2.jpg", "PastGovernment": true, "PastOpposition": false}, {"Name": "ภานุวัตร นักรบ", "Birthdate": "2015-11-27", "Number": 7, "Education": "ด้อกเต้อ", "ExOccupation": "อธิบดีกรมการแพทย์", "Party": "ความหวังใหม่", "Province": "อุดรธานี", "Zone": 8, "Image": "", "PastGovernment": false, "PastOpposition": false}, {"Name": "เทวัญ ลิปตพัลลภ", "Birthdate": "1985-01-24", "Number": 8, "Education": "อิฟลู", "ExOccupation": "ที่ปรึกษาคณะรักษาความสงบแห่งชาติ (คสช.)", "Party": "ประชาธิปัตย์", "Province": "อุดรธานี", "Zone": 8, "Image": "https://sheets.wevis.info/download/noco/They-Work-For-Us/People/Images/%E0%B8%A7%E0%B8%B1%E0%B8%92%E0%B8%99%E0%B8%B2-%E0%B8%8A%E0%B9%88%E0%B8%B2%E0%B8%87%E0%B9%80%E0%B8%AB%E0%B8%A5%E0%B8%B2.jpg", "PastGovernment": false, "PastOpposition": true}, {"Name": "วนาลี ถนัดกลึง", "Birthdate": "1986-03-06", "Number": 9, "Education": "ปริญญาโท", "ExOccupation": "สมาชิกสภาผู้แทนราษฎร", "Party": "เศรษฐกิจใหม่", "Province": "อุดรธานี", "Zone": 8, "Image": "", "PastGovernment": false, "PastOpposition": true}, {"Name": "รังสรรค์ มณีรัตน์", "Birthdate": "1970-02-04", "Number": 10, "Education": "อิฟลู", "ExOccupation": "รองนายกรัฐมนตรีฝ่ายความมั่นคง", "Party": "พลังสหกรณ์", "Province": "อุดรธานี", "Zone": 8, "Image": "https://sheets.wevis.info/download/noco/They-Work-For-Us/People/Images/%E0%B8%9E%E0%B8%B4%E0%B8%9E%E0%B8%B1%E0%B8%92%E0%B8%99%E0%B9%8C-%E0%B8%A3%E0%B8%B1%E0%B8%8A%E0%B8%81%E0%B8%B4%E0%B8%88%E0%B8%9B%E0%B8%A3%E0%B8%B0%E0%B8%81%E0%B8%B2%E0%B8%A3.jpg", "PastGovernment": false, "PastOpposition": false}, {"Name": "จักรพันธ์ นาคสุทิน", "Birthdate": "2006-04-03", "Number": 11, "Education": "ปริญญาเอก", "ExOccupation": "ข้าราชการตำรวจ", "Party": "ไทรักธรรม", "Province": "อุดรธานี", "Zone": 8, "Image": "", "PastGovernment": false, "PastOpposition": true}, {"Name": "มัลลิกา จิระพันธุ์วาณิช", "Birthdate": "1990-01-22", "Number": 12, "Education": "อิฟลู", "ExOccupation": "สมาชิกวุฒิสภาจังหวัดเพชรบุรี", "Party": "ไทยภักดี", "Province": "อุดรธานี", "Zone": 8, "Image": "https://sheets.wevis.info/download/noco/They-Work-For-Us/People/Images/%E0%B8%AA%E0%B8%A1%E0%B8%9A%E0%B8%B1%E0%B8%95%E0%B8%B4-%E0%B8%AD%E0%B8%B3%E0%B8%99%E0%B8%B2%E0%B8%84%E0%B8%B0.jpg", "PastGovernment": false, "PastOpposition": false}, {"Name": "กุลปรียา จันอ้น", "Birthdate": "1988-10-04", "Number": 13, "Education": "ปริญญาตรี", "ExOccupation": "รองนายกองค์การบริหารส่วนจังหวัดตาก", "Party": "พลังธรรมใหม่", "Province": "อุดรธานี", "Zone": 8, "Image": "", "PastGovernment": false, "PastOpposition": false}, {"Name": "มลิวรรณ เณรานุสนธิ์", "Birthdate": "2004-10-28", "Number": 14, "Education": "อิฟลู", "ExOccupation": "นักกฏหมาย", "Party": "เพื่อไทย", "Province": "อุดรธานี", "Zone": 8, "Image": "", "PastGovernment": false, "PastOpposition": true}, {"Name": "ศักดา คงเพชร", "Birthdate": "1970-02-17", "Number": 15, "Education": "ปริญญาตรี", "ExOccupation": "สมาชิกสภาองค์การบริหารส่วนจังหวัดสุโขทัย", "Party": "ไทยธรรม", "Province": "อุดรธานี", "Zone": 8, "Image": "https://sheets.wevis.info/download/noco/They-Work-For-Us/People/Images/%E0%B8%81%E0%B8%B8%E0%B8%A5%E0%B8%98%E0%B8%B4%E0%B8%94%E0%B8%B2-%E0%B8%A3%E0%B8%B8%E0%B9%88%E0%B8%87%E0%B9%80%E0%B8%A3%E0%B8%B7%E0%B8%AD%E0%B8%87%E0%B9%80%E0%B8%81%E0%B8%B5%E0%B8%A2%E0%B8%A3%E0%B8%95%E0%B8%B4.jpg", "PastGovernment": false, "PastOpposition": true}, {"Name": "ธีราทัต ศรทอง", "Birthdate": "1993-02-21", "Number": 16, "Education": "ปริญญาตรี", "ExOccupation": "ผู้เชี่ยวชาญประจำตัวสมาชิกสภาผู้แทนราษฎร", "Party": "ประชาธิปไตยใหม่", "Province": "อุดรธานี", "Zone": 8, "Image": "https://sheets.wevis.info/download/noco/They-Work-For-Us/People/Images/%E0%B8%AA%E0%B8%A1%E0%B8%8A%E0%B8%B2%E0%B8%95%E0%B8%B4-%E0%B8%9B%E0%B8%A3%E0%B8%B0%E0%B8%94%E0%B8%B4%E0%B8%A9%E0%B8%90%E0%B8%9E%E0%B8%A3.jpg", "PastGovernment": true, "PastOpposition": true}, {"Name": "ณัฐญาดา อุ่นอก", "Birthdate": "1982-09-13", "Number": 17, "Education": "ปริญญาโท", "ExOccupation": "ที่ปรึกษาธุรกิจอิสระ", "Party": "รวมไทยสร้างชาติ", "Province": "อุดรธานี", "Zone": 8, "Image": "https://sheets.wevis.info/download/noco/They-Work-For-Us/People/Images/%E0%B8%81%E0%B8%B4%E0%B8%95%E0%B8%95%E0%B8%B4%E0%B8%9B%E0%B8%A3%E0%B8%B0%E0%B8%A0%E0%B8%B2-%E0%B8%88%E0%B8%B4%E0%B8%A7%E0%B8%B0%E0%B8%AA%E0%B8%B1%E0%B8%99%E0%B8%95%E0%B8%B4%E0%B8%81%E0%B8%B2%E0%B8%A3.jpg", "PastGovernment": false, "PastOpposition": true}, {"Name": "มานัส อ่อนอ้าย", "Birthdate": "2016-11-18", "Number": 18, "Education": "ปริญญาตรี", "ExOccupation": "ประธานสภาองค์การบริหารส่วนจังหวัดสุราษฎร์ธานี", "Party": "ก้าวไกล", "Province": "อุดรธานี", "Zone": 8, "Image": "", "PastGovernment": true, "PastOpposition": false}, {"Name": "ภานุ ศรีบุศยกาญจน์", "Birthdate": "1992-02-02", "Number": 19, "Education": "ปริญญาโท", "ExOccupation": "นักวิชาการพาณิชย์ กรมเจรจาการค้าระหว่างประเทศ", "Party": "ประชาไทย", "Province": "อุดรธานี", "Zone": 8, "Image": "https://sheets.wevis.info/download/noco/They-Work-For-Us/People/Images/%E0%B8%84%E0%B8%B8%E0%B8%93%E0%B8%B2%E0%B8%81%E0%B8%A3-%E0%B8%9B%E0%B8%A3%E0%B8%B5%E0%B8%8A%E0%B8%B2%E0%B8%8A%E0%B8%99%E0%B8%B0%E0%B8%8A%E0%B8%B1%E0%B8%A2.jpg", "PastGovernment": true, "PastOpposition": true}, {"Name": "ประยุทธ์ จันทร์โอชา", "Birthdate": "1996-10-15", "Number": 20, "Education": "อิฟลู", "ExOccupation": "ผู้ช่วยรัฐมนตรีว่าการกระทรวงการคลัง", "Party": "รวมแผ่นดิน", "Province": "อุดรธานี", "Zone": 8, "Image": "https://sheets.wevis.info/download/noco/They-Work-For-Us/People/Images/%E0%B9%80%E0%B8%81%E0%B8%B5%E0%B8%A2%E0%B8%A3%E0%B8%95%E0%B8%B4-%E0%B9%80%E0%B8%AB%E0%B8%A5%E0%B8%B7%E0%B8%AD%E0%B8%87%E0%B8%82%E0%B8%88%E0%B8%A3%E0%B8%A7%E0%B8%B4%E0%B8%97%E0%B8%A2%E0%B9%8C.jpg", "PastGovernment": false, "PastOpposition": true}, {"Name": "คมสัน นาถะพินธุ", "Birthdate": "1999-10-22", "Number": 21, "Education": "ปริญญาจัตวา", "ExOccupation": "ผู้อำนวยการศูนย์เรียนรู้", "Party": "เศรษฐกิจไทย", "Province": "อุดรธานี", "Zone": 8, "Image": "", "PastGovernment": false, "PastOpposition": true}, {"Name": "เสมอกัน เที่ยงธรรม", "Birthdate": "1985-04-09", "Number": 22, "Education": "ปริญญาโท", "ExOccupation": "ผู้อำนวยการศูนย์อำนวยการบริหารจังหวัดชายแดนภาคใต้", "Party": "ประชาสามัคคี", "Province": "อุดรธานี", "Zone": 8, "Image": "", "PastGovernment": false, "PastOpposition": true}, {"Name": "ปริญญา หอมสิน", "Birthdate": "1976-01-19", "Number": 23, "Education": "อิฟลู", "ExOccupation": "สัตวแพทย์", "Party": "พลเมืองไทย", "Province": "อุดรธานี", "Zone": 8, "Image": "", "PastGovernment": false, "PastOpposition": true}, {"Name": "คำปลิว ตันเผ่า", "Birthdate": "1978-07-15", "Number": 24, "Education": "ปริญญาจัตวา", "ExOccupation": "รัฐมนตรีช่วยว่าการกระทรวงคมนาคม", "Party": "คนงานไทย", "Province": "อุดรธานี", "Zone": 8, "Image": "", "PastGovernment": false, "PastOpposition": true}, {"Name": "โชติพิพัฒน์ เตชะโสภณมณี", "Birthdate": "1985-12-16", "Number": 25, "Education": "ปริญญาโท", "ExOccupation": "ผู้บัญชาการทหารบก", "Party": "พลังประชาธิปไตย", "Province": "อุดรธานี", "Zone": 8, "Image": "https://sheets.wevis.info/download/noco/They-Work-For-Us/People/Images/%E0%B8%A1%E0%B8%B2%E0%B8%99%E0%B8%B0%E0%B8%A8%E0%B8%B1%E0%B8%81%E0%B8%94%E0%B8%B4%E0%B9%8C-%E0%B8%88%E0%B8%B1%E0%B8%99%E0%B8%97%E0%B8%A3%E0%B9%8C%E0%B8%9B%E0%B8%A3%E0%B8%B0%E0%B8%AA%E0%B8%87%E0%B8%84%E0%B9%8C.jpg", "PastGovernment": false, "PastOpposition": true}, {"Name": "วีระพล จิตสัมฤทธิ์", "Birthdate": "2012-09-11", "Number": 26, "Education": "ปริญญาจัตวา", "ExOccupation": "รัฐมนตรีว่าการกระทรวงอุตสาหกรรม", "Party": "ภาคีเครือข่ายไทย", "Province": "อุดรธานี", "Zone": 8, "Image": "https://sheets.wevis.info/download/noco/They-Work-For-Us/People/Images/%E0%B8%9B%E0%B8%A3%E0%B8%B0%E0%B8%A2%E0%B8%B8%E0%B8%97%E0%B8%98%E0%B9%8C-%E0%B8%88%E0%B8%B1%E0%B8%99%E0%B8%97%E0%B8%A3%E0%B9%8C%E0%B9%82%E0%B8%AD%E0%B8%8A%E0%B8%B2.jpg", "PastGovernment": false, "PastOpposition": true}, {"Name": "อนุพร อรุณรัตน์", "Birthdate": "2018-10-17", "Number": 27, "Education": "ด้อกเต้อ", "ExOccupation": "ผู้จัดการทีมสโมสรฟุตบอลนครปฐม ยูไนเต็ด", "Party": "เครือข่ายชาวนาแห่งประเทศไทย", "Province": "อุดรธานี", "Zone": 8, "Image": "https://sheets.wevis.info/download/noco/They-Work-For-Us/People/Images/%E0%B8%97%E0%B8%B1%E0%B8%A8%E0%B8%99%E0%B8%B5%E0%B8%A2%E0%B9%8C-%E0%B8%9A%E0%B8%B9%E0%B8%A3%E0%B8%93%E0%B8%B8%E0%B8%9B%E0%B8%81%E0%B8%A3%E0%B8%93%E0%B9%8C.jpg", "PastGovernment": false, "PastOpposition": true}], "Parties": ["รักษ์ผืนป่าประเทศไทย", "ทางเลือกใหม่", "พลังปวงชนไทย", "ภูมิใจไทย", "พลังสังคม", "รวมพลัง", "ความหวังใหม่", "ประชาธิปัตย์", "เศรษฐกิจใหม่", "พลังสหกรณ์", "ไทรักธรรม", "ไทยภักดี", "พลังธรรมใหม่", "เพื่อไทย", "ไทยธรรม", "ประชาธิปไตยใหม่", "รวมไทยสร้างชาติ", "ก้าวไกล", "ประชาไทย", "รวมแผ่นดิน", "เศรษฐกิจไทย", "ประชาสามัคคี", "พลเมืองไทย", "คนงานไทย", "พลังประชาธิปไตย", "ภาคีเครือข่ายไทย", "เครือข่ายชาวนาแห่งประเทศไทย"]}