[
	{
		"full_address": "2439 ถนนริมทางรถไฟสายปากน้ำ แขวงพระโขนง เขตคลองเตย กรุงเทพมหานคร",
		"financial": [
			{ "year": "2565", "income": 24882811.9100000001 },
			{ "year": "2564", "income": 23132487.2899999991 },
			{ "year": "2563", "income": 21888280.8900000006 },
			{ "year": "2562", "income": 22102248.6799999997 }
		],
		"value_share": 5701393,
		"submit_obj_big_type": "H",
		"company_name_th": "ซี.เอ็ม.ชูติมาศ จำกัด",
		"pct_share": 9.9905,
		"obj_tname": "กิจกรรมที่เกี่ยวกับคลังสินค้าและการจัดเก็บสินค้าอื่นๆซึ่งมิได้จัดประเภทไว้ในที่อื่น",
		"company_id": "0105525019468",
		"reg_date": "7/6/2525",
		"company_name_en": "",
		"tsic": 52109,
		"cap_amt": 19999000,
		"company_value": 57068147,
		"company_type_th": "บริษัทจำกัด",
		"company_shareholder": [
			{
				"Lastname": "จิตติมิต",
				"value_share": 5045053,
				"Nationality": "TH",
				"pct_share": 8.84,
				"count_share": 1768,
				"Firstname": "จุฑามาศ"
			},
			{
				"Lastname": "หิมะทองคำ",
				"value_share": 282487,
				"Nationality": "TH",
				"pct_share": 0.49,
				"count_share": 99,
				"Firstname": "อาทิมา"
			},
			{
				"Lastname": "หิมะทองคำ",
				"value_share": 285341,
				"Nationality": "TH",
				"pct_share": 0.5,
				"count_share": 100,
				"Firstname": "กุนทรี"
			},
			{
				"Lastname": "หิมะทองคำ",
				"value_share": 282487,
				"Nationality": "TH",
				"pct_share": 0.49,
				"count_share": 99,
				"Firstname": "อภิชัย"
			},
			{
				"Lastname": "หิมะทองคำ",
				"value_share": 282487,
				"Nationality": "TH",
				"pct_share": 0.49,
				"count_share": 99,
				"Firstname": "พริมา เจสซิก้า"
			},
			{
				"Lastname": "จิตติมิต",
				"value_share": 4280339,
				"Nationality": "TH",
				"pct_share": 7.5,
				"count_share": 1500,
				"Firstname": "บรรหาร"
			},
			{
				"Lastname": "หิมะทองคำ",
				"value_share": 282487,
				"Nationality": "TH",
				"pct_share": 0.49,
				"count_share": 99,
				"Firstname": "ณัฐริญา"
			},
			{
				"Lastname": "หิมะทองคำ",
				"value_share": 576445,
				"Nationality": "TH",
				"pct_share": 1.01,
				"count_share": 202,
				"Firstname": "เจน"
			},
			{
				"Lastname": "หิมะทองคำ",
				"value_share": 5701393,
				"Nationality": "TH",
				"pct_share": 9.99,
				"count_share": 1998,
				"Firstname": "ภักดีหาญส์",
				"person": {
					"Number": 8,
					"Title": "นาย",
					"Name": "ภักดีหาญส์ หิมะทองคำ",
					"PartyName": "พลังประชารัฐ",
					"MpType": "แบ่งเขต",
					"Id": "2062",
					"IsMp": true,
					"IsActive": true,
					"IsSanator": false,
					"IsCabinet": false,
					"IsPmCandidate": false,
					"MpProvince": "กรุงเทพมหานคร",
					"MpZone": 13,
					"MpList": "",
					"Images": "/mpasset/candidates/พลังประชารัฐ/ภักดีหาญส์-หิมะทองคำ.webp",
					"Party": {
						"Name": "พลังประชารัฐ",
						"Color": "#2276EF",
						"PartyType": "พรรค",
						"IsActive": true,
						"Id": 20,
						"Images": "https://sheets.wevis.info/download/noco/They-Work-For-Us/Parties/Images/Y8aiwU_p-C-aZyw_PN.png"
					},
					"companyType": [],
					"totalValueShare": 0,
					"countCompShare": 0,
					"countDirector": 0,
					"totalPctShare": 0
				}
			},
			{
				"Lastname": "หิมะทองคำ",
				"value_share": 6640221,
				"Nationality": "TH",
				"pct_share": 11.64,
				"count_share": 2327,
				"Firstname": "ชูศักดิ์"
			},
			{
				"Lastname": "หิมะทองคำ",
				"value_share": 282487,
				"Nationality": "TH",
				"pct_share": 0.49,
				"count_share": 99,
				"Firstname": "เอมมิกา"
			},
			{
				"Lastname": "หิมะทองคำ",
				"value_share": 282487,
				"Nationality": "TH",
				"pct_share": 0.49,
				"count_share": 99,
				"Firstname": "พงศภัค"
			},
			{
				"Lastname": "หิมะทองคำ",
				"value_share": 282487,
				"Nationality": "TH",
				"pct_share": 0.49,
				"count_share": 99,
				"Firstname": "ภัคธิมา เพิร์ล"
			},
			{
				"Lastname": "หิมะทองคำ",
				"value_share": 539294,
				"Nationality": "TH",
				"pct_share": 0.94,
				"count_share": 189,
				"Firstname": "สุปราณี"
			},
			{
				"Lastname": "หิมะทองคำ",
				"value_share": 282487,
				"Nationality": "TH",
				"pct_share": 0.49,
				"count_share": 99,
				"Firstname": "ภีมเดช เพียซ"
			},
			{
				"Lastname": "จิตติมิต",
				"value_share": 282487,
				"Nationality": "TH",
				"pct_share": 0.49,
				"count_share": 99,
				"Firstname": "ชวัลวิชญ์"
			},
			{
				"Lastname": "หิมะทองคำ",
				"value_share": 285341,
				"Nationality": "TH",
				"pct_share": 0.5,
				"count_share": 100,
				"Firstname": "พัชรี"
			},
			{
				"Lastname": "หิมะทองคำ",
				"value_share": 5701393,
				"Nationality": "TH",
				"pct_share": 9.99,
				"count_share": 1998,
				"Firstname": "ธเนศร์เศียร"
			},
			{
				"Lastname": "หิมะทองคำ",
				"value_share": 282487,
				"Nationality": "TH",
				"pct_share": 0.49,
				"count_share": 99,
				"Firstname": "ปาณิสรา"
			},
			{
				"Lastname": "จิตติมิต",
				"value_share": 4280339,
				"Nationality": "TH",
				"pct_share": 7.5,
				"count_share": 1500,
				"Firstname": "ศุภโชค"
			},
			{
				"Lastname": "ปุกหุต",
				"value_share": 85602,
				"Nationality": "TH",
				"pct_share": 0.15,
				"count_share": 30,
				"Firstname": "นพรัตน์"
			},
			{
				"Lastname": "จิตติมิต",
				"value_share": 1147127,
				"Nationality": "TH",
				"pct_share": 2.01,
				"count_share": 402,
				"Firstname": "เทอดศักดิ์"
			},
			{
				"Lastname": "หิมะทองคำ",
				"value_share": 5701393,
				"Nationality": "TH",
				"pct_share": 9.99,
				"count_share": 1998,
				"Firstname": "จาตุรนต์ เซนน์"
			},
			{
				"Lastname": "จิตติมิต",
				"value_share": 282487,
				"Nationality": "TH",
				"pct_share": 0.49,
				"count_share": 99,
				"Firstname": "สรสิช"
			},
			{
				"Lastname": "หิมะทองคำ",
				"value_share": 5701393,
				"Nationality": "TH",
				"pct_share": 9.99,
				"count_share": 1998,
				"Firstname": "พรศักดิ์ จวรณ์"
			},
			{
				"Lastname": "หิมะทองคำ",
				"value_share": 3144626,
				"Nationality": "TH",
				"pct_share": 5.51,
				"count_share": 1102,
				"Firstname": "มาร์กาเร็ต โจน"
			},
			{
				"Lastname": "หิมะทองคำ",
				"value_share": 282487,
				"Nationality": "TH",
				"pct_share": 0.49,
				"count_share": 99,
				"Firstname": "ภีมวัจน์ พอล"
			},
			{
				"Lastname": "หิมะทองคำ",
				"value_share": 282487,
				"Nationality": "TH",
				"pct_share": 0.49,
				"count_share": 99,
				"Firstname": "นัทชา แอลีน่า"
			},
			{
				"Lastname": "จิตติมิต",
				"value_share": 4280339,
				"Nationality": "TH",
				"pct_share": 7.5,
				"count_share": 1500,
				"Firstname": "จิรายุทธ์"
			}
		],
		"count_shareholder": 1998,
		"gov_fund_proj": null
	},
	{
		"full_address": "2439 ถนนริมทางรถไฟสายปากน้ำ แขวงพระโขนง เขตคลองเตย กรุงเทพมหานคร",
		"financial": [
			{ "year": "2564", "income": 6209400 },
			{ "year": "2563", "income": 6058095.0099999998 },
			{ "year": "2562", "income": 6007650 },
			{ "year": "2561", "income": 6371160 }
		],
		"value_share": 132020,
		"submit_obj_big_type": "M",
		"company_name_th": "โซลิค ทรีโอ เทรดดิ้ง จำกัด",
		"pct_share": 10.0,
		"obj_tname": "กิจกรรมของบริษัทโฆษณา",
		"company_id": "0105540075586",
		"reg_date": "21/08/2540",
		"company_name_en": "SOLID TRIO TRADING COMPANY LIMITED",
		"tsic": 73101,
		"cap_amt": 1000000,
		"company_value": 1320202,
		"company_type_th": "บริษัทจำกัด",
		"company_shareholder": [
			{
				"Lastname": "หิมะทองคำ",
				"value_share": 132020,
				"Nationality": "TH",
				"pct_share": 10,
				"count_share": 1000,
				"Firstname": "พรศักดิ์จวรณ์"
			},
			{
				"Lastname": "หิมะทองคำ",
				"value_share": 330050,
				"Nationality": "TH",
				"pct_share": 25,
				"count_share": 2500,
				"Firstname": "จาตุรนต์ เซนน์"
			},
			{
				"Lastname": "หิมะทองคำ",
				"value_share": 66010,
				"Nationality": "TH",
				"pct_share": 5,
				"count_share": 500,
				"Firstname": "ปอรนุช"
			},
			{
				"Lastname": "หิมะทองคำ",
				"value_share": 330050,
				"Nationality": "TH",
				"pct_share": 25,
				"count_share": 2500,
				"Firstname": "ธเนศร์ เศียร"
			},
			{
				"Lastname": "หิมะทองคำ",
				"value_share": 330050,
				"Nationality": "TH",
				"pct_share": 25,
				"count_share": 2500,
				"Firstname": "ชูศักดิ์"
			},
			{
				"Lastname": "หิมะทองคำ",
				"value_share": 132020,
				"Nationality": "TH",
				"pct_share": 10,
				"count_share": 1000,
				"Firstname": "ภักดีหาญส์",
				"person": {
					"Number": 8,
					"Title": "นาย",
					"Name": "ภักดีหาญส์ หิมะทองคำ",
					"PartyName": "พลังประชารัฐ",
					"MpType": "แบ่งเขต",
					"Id": "2062",
					"IsMp": true,
					"IsActive": true,
					"IsSanator": false,
					"IsCabinet": false,
					"IsPmCandidate": false,
					"MpProvince": "กรุงเทพมหานคร",
					"MpZone": 13,
					"MpList": "",
					"Images": "/mpasset/candidates/พลังประชารัฐ/ภักดีหาญส์-หิมะทองคำ.webp",
					"Party": {
						"Name": "พลังประชารัฐ",
						"Color": "#2276EF",
						"PartyType": "พรรค",
						"IsActive": true,
						"Id": 20,
						"Images": "https://sheets.wevis.info/download/noco/They-Work-For-Us/Parties/Images/Y8aiwU_p-C-aZyw_PN.png"
					},
					"companyType": [],
					"totalValueShare": 0,
					"countCompShare": 0,
					"countDirector": 0,
					"totalPctShare": 0
				}
			}
		],
		"count_shareholder": 1000,
		"gov_fund_proj": null
	},
	{
		"full_address": "2439 ถนนริมทางรถไฟสายปากน้ำ แขวงพระโขนง เขตคลองเตย กรุงเทพมหานคร",
		"financial": [
			{ "year": "2564", "income": 96.34 },
			{ "year": "2563", "income": 414.75 },
			{ "year": "2562", "income": 419080.48 },
			{ "year": "2561", "income": 249549.95 }
		],
		"value_share": 7727495,
		"submit_obj_big_type": "L",
		"company_name_th": "รวมทองแลนด์ แอนด์ เฮ้าส์ จำกัด",
		"pct_share": 20.0,
		"obj_tname": "การซื้อและการขายอสังหาริมทรัพย์ที่เป็นของตนเอง เพื่อการพักอาศัย",
		"company_id": "0105535122041",
		"reg_date": "31/8/2535",
		"company_name_en": "RUAMTHONGLAND AND HOUSE CO., LTD.",
		"tsic": 68101,
		"cap_amt": 12000000,
		"company_value": 38637477,
		"company_type_th": "บริษัทจำกัด",
		"company_shareholder": [
			{
				"Lastname": "หิมะทองคำ",
				"value_share": 7727495,
				"Nationality": "TH",
				"pct_share": 20,
				"count_share": 24000,
				"Firstname": "จาตุรนต์ เซนน์"
			},
			{
				"Lastname": "หิมะทองคำ",
				"value_share": 7727495,
				"Nationality": "TH",
				"pct_share": 20,
				"count_share": 24000,
				"Firstname": "พรศักดิ์จวรณ์"
			},
			{
				"Lastname": "หิมะทองคำ",
				"value_share": 7727495,
				"Nationality": "TH",
				"pct_share": 20,
				"count_share": 24000,
				"Firstname": "ชูศักดิ์"
			},
			{
				"Lastname": "หิมะทองคำ",
				"value_share": 7727495,
				"Nationality": "TH",
				"pct_share": 20,
				"count_share": 24000,
				"Firstname": "ภักดีหาญส์",
				"person": {
					"Number": 8,
					"Title": "นาย",
					"Name": "ภักดีหาญส์ หิมะทองคำ",
					"PartyName": "พลังประชารัฐ",
					"MpType": "แบ่งเขต",
					"Id": "2062",
					"IsMp": true,
					"IsActive": true,
					"IsSanator": false,
					"IsCabinet": false,
					"IsPmCandidate": false,
					"MpProvince": "กรุงเทพมหานคร",
					"MpZone": 13,
					"MpList": "",
					"Images": "/mpasset/candidates/พลังประชารัฐ/ภักดีหาญส์-หิมะทองคำ.webp",
					"Party": {
						"Name": "พลังประชารัฐ",
						"Color": "#2276EF",
						"PartyType": "พรรค",
						"IsActive": true,
						"Id": 20,
						"Images": "https://sheets.wevis.info/download/noco/They-Work-For-Us/Parties/Images/Y8aiwU_p-C-aZyw_PN.png"
					},
					"companyType": [],
					"totalValueShare": 0,
					"countCompShare": 0,
					"countDirector": 0,
					"totalPctShare": 0
				}
			},
			{
				"Lastname": "หิมะทองคำ",
				"value_share": 7727495,
				"Nationality": "TH",
				"pct_share": 20,
				"count_share": 24000,
				"Firstname": "ธเนศร์ เศียร"
			}
		],
		"count_shareholder": 24000,
		"gov_fund_proj": null
	},
	{
		"full_address": "2439 ถนนริมทางรถไฟเก่าสายปากน้ำ แขวงพระโขนง เขตคลองเตย กรุงเทพมหานคร",
		"financial": [
			{ "year": "2564", "income": 0 },
			{ "year": "2563", "income": 0 },
			{ "year": "2562", "income": 0 },
			{ "year": "2561", "income": 0 }
		],
		"value_share": -1523340,
		"submit_obj_big_type": "H",
		"company_name_th": "ซี.เอ็ม.คลังสินค้า จำกัด",
		"pct_share": 20.0,
		"obj_tname": "กิจกรรมที่เกี่ยวกับคลังสินค้าและการจัดเก็บสินค้าอื่นๆซึ่งมิได้จัดประเภทไว้ในที่อื่น",
		"company_id": "0105530023559",
		"reg_date": "19/5/2530",
		"company_name_en": "C.M. WAREHOUSE CO., LTD.",
		"tsic": 52109,
		"cap_amt": 5000000,
		"company_value": -7616698,
		"company_type_th": "บริษัทจำกัด",
		"company_shareholder": [
			{
				"Lastname": "หิมะทองคำ",
				"value_share": -1521816,
				"Nationality": "TH",
				"pct_share": 19.98,
				"count_share": 999,
				"Firstname": "ธเนศร์ เศียร"
			},
			{
				"Lastname": "หิมะทองคำ",
				"value_share": -1523340,
				"Nationality": "TH",
				"pct_share": 20,
				"count_share": 1000,
				"Firstname": "ภักดีหาญส์",
				"person": {
					"Number": 8,
					"Title": "นาย",
					"Name": "ภักดีหาญส์ หิมะทองคำ",
					"PartyName": "พลังประชารัฐ",
					"MpType": "แบ่งเขต",
					"Id": "2062",
					"IsMp": true,
					"IsActive": true,
					"IsSanator": false,
					"IsCabinet": false,
					"IsPmCandidate": false,
					"MpProvince": "กรุงเทพมหานคร",
					"MpZone": 13,
					"MpList": "",
					"Images": "/mpasset/candidates/พลังประชารัฐ/ภักดีหาญส์-หิมะทองคำ.webp",
					"Party": {
						"Name": "พลังประชารัฐ",
						"Color": "#2276EF",
						"PartyType": "พรรค",
						"IsActive": true,
						"Id": 20,
						"Images": "https://sheets.wevis.info/download/noco/They-Work-For-Us/Parties/Images/Y8aiwU_p-C-aZyw_PN.png"
					},
					"companyType": [],
					"totalValueShare": 0,
					"countCompShare": 0,
					"countDirector": 0,
					"totalPctShare": 0
				}
			},
			{
				"Lastname": "หิมะทองคำ",
				"value_share": -1523,
				"Nationality": "TH",
				"pct_share": 0.02,
				"count_share": 1,
				"Firstname": "ปอรนุช"
			},
			{
				"Lastname": "หิมะทองคำ",
				"value_share": -1523,
				"Nationality": "TH",
				"pct_share": 0.02,
				"count_share": 1,
				"Firstname": "อแมนด้า"
			},
			{
				"Lastname": "หิมะทองคำ",
				"value_share": -1521816,
				"Nationality": "TH",
				"pct_share": 19.98,
				"count_share": 999,
				"Firstname": "พรศักดิ์จวรณ์"
			},
			{
				"Lastname": "หิมะทองคำ",
				"value_share": -1521816,
				"Nationality": "TH",
				"pct_share": 19.98,
				"count_share": 999,
				"Firstname": "ชูศักดิ์"
			},
			{
				"Lastname": "หิมะทองคำ",
				"value_share": -1523,
				"Nationality": "TH",
				"pct_share": 0.02,
				"count_share": 1,
				"Firstname": "มาร์กาเร็ต โจน"
			},
			{
				"Lastname": "หิมะทองคำ",
				"value_share": -1521816,
				"Nationality": "TH",
				"pct_share": 19.98,
				"count_share": 999,
				"Firstname": "จาตุรนต์ เซนน์"
			},
			{
				"Lastname": "หิมะทองคำ",
				"value_share": -1523,
				"Nationality": "TH",
				"pct_share": 0.02,
				"count_share": 1,
				"Firstname": "มณีรัตน์"
			}
		],
		"count_shareholder": 1000,
		"gov_fund_proj": null
	},
	{
		"full_address": "2439 ถนนริมทางรถไฟสายปากน้ำ แขวงพระโขนง เขตคลองเตย กรุงเทพมหานคร",
		"financial": [
			{ "year": "2564", "income": 12000 },
			{ "year": "2563", "income": 299636.22 },
			{ "year": "2562", "income": 0 },
			{ "year": "2561", "income": 9371868.9299999997 }
		],
		"value_share": -1233025,
		"submit_obj_big_type": "M",
		"company_name_th": "ดรีมแคสท์ โปรดักชั่น จำกัด",
		"pct_share": 25.0,
		"obj_tname": "กิจกรรมของบริษัทโฆษณา",
		"company_id": "0105542062082",
		"reg_date": "20/8/2542",
		"company_name_en": "DREAM CAST PRODUCTION CO., LTD.",
		"tsic": 73101,
		"cap_amt": 3000000,
		"company_value": -4932101,
		"company_type_th": "บริษัทจำกัด",
		"company_shareholder": [
			{
				"Lastname": "หิมะทองคำ",
				"value_share": -164402,
				"Nationality": "TH",
				"pct_share": 3.33,
				"count_share": 1000,
				"Firstname": "จาตุรนต์ เซนน์"
			},
			{
				"Lastname": "หิมะทองคำ",
				"value_share": -49321,
				"Nationality": "TH",
				"pct_share": 1,
				"count_share": 300,
				"Firstname": "อแมนด้า"
			},
			{
				"Lastname": "หิมะทองคำ",
				"value_share": -986420,
				"Nationality": "TH",
				"pct_share": 20,
				"count_share": 6000,
				"Firstname": "ชูศักดิ์"
			},
			{
				"Lastname": "หิมะทองคำ",
				"value_share": -2005723,
				"Nationality": "TH",
				"pct_share": 40.67,
				"count_share": 12200,
				"Firstname": "พรศักดิ์ จวรณ์"
			},
			{
				"Lastname": "หิมะทองคำ",
				"value_share": -443889,
				"Nationality": "TH",
				"pct_share": 9,
				"count_share": 2700,
				"Firstname": "ธเนศร์ เศียร"
			},
			{
				"Lastname": "หิมะทองคำ",
				"value_share": -49321,
				"Nationality": "TH",
				"pct_share": 1,
				"count_share": 300,
				"Firstname": "ปอรนุช"
			},
			{
				"Lastname": "หิมะทองคำ",
				"value_share": -1233025,
				"Nationality": "TH",
				"pct_share": 25,
				"count_share": 7500,
				"Firstname": "ภักดี หาญส์"
			}
		],
		"count_shareholder": 7500,
		"gov_fund_proj": null
	}
]
