[{"company_shareholder":{},"full_address":"88\/164 หมู่บ้านชวนชื่น วัชรพล หมู่ที่ 8 ซอยรามอินทรา 65 ถนนรามอินทรา  แขวงท่าแร้ง เขตบางเขน กรุงเทพมหานคร","submit_obj_big_type":"S","company_name_th":"519 พันล้าน จำกัด","company_id":"0105553065266","reg_date":"31\/05\/2553","company_name_en":"519 PUN LARN CO.,LTD.","tsic":96101,"cap_amt":1000000,"company_value":589904,"company_type_th":"บริษัทจำกัด","financial":[{"year":"2558","income":11533.15},{"year":"2557","income":11733.15},{"year":"2556","income":0},{"year":"2555","income":7.77}],"obj_tname":"กิจกรรมสปา","gov_fund_proj":null}]