[{"financial":[{"year":"2564","income":2023899356.5299999714},{"year":"2563","income":1910964487.1800000668},{"year":"2562","income":2026644815.4000000954},{"year":"2561","income":1957532298.5499999523}],"company_shareholder":{},"reg_date":"01\/12\/2547","company_name_th":"เอี่ยมศิริแป้งมัน จำกัด","company_id":"0275547000203","obj_tname":"การผลิตสตาร์ชมันสำปะหลัง","company_name_en":"EIAMSIRI STARCH COMPANY LIMITED","tsic":10622,"cap_amt":600000000,"company_value":734569956,"company_type_th":"บริษัทจำกัด","submit_obj_big_type":"C","full_address":"49 หมู่ที่ 11  ต.จานใหญ่ อ.กันทรลักษ์ จ.ศรีสะเกษ","gov_fund_proj":null},{"financial":[{"year":"2564","income":69971949.3299999982},{"year":"2563","income":59047137.8200000003},{"year":"2562","income":54365762.6700000018},{"year":"2561","income":50908875.6199999973}],"company_shareholder":{},"reg_date":"12\/09\/2544","company_name_th":"เกียรติโกศล จำกัด","company_id":"0305544000848","obj_tname":"การขนส่งสินค้าอื่นๆทางถนนซึ่งมิได้จัดประเภทไว้ในที่อื่น","company_name_en":"KREATKOSOL COMPANY LIMITED","tsic":49339,"cap_amt":18000000,"company_value":-39340842,"company_type_th":"บริษัทจำกัด","submit_obj_big_type":"H","full_address":"117 หมู่ที่ 3  ต.กุดโบสถ์ อ.เสิงสาง จ.นครราชสีมา","gov_fund_proj":null},{"financial":[{"year":"2564","income":125964.51},{"year":"2563","income":145140.71},{"year":"2562","income":52948.89},{"year":"2561","income":940.64}],"company_shareholder":{},"reg_date":"8\/9\/2560","company_name_th":"ทีทีเจ โมดิฟายสตาร์ช จำกัด","company_id":"0335560000750","obj_tname":"การผลิตผลิตภัณฑ์จากสตาร์ชอื่น ๆ ซึ่งมิได้จัดประเภทไว้ในที่อื่น","company_name_en":"TTJ MODIFIED STARCH COMPANY LIMITED","tsic":10629,"cap_amt":125000000,"company_value":31729482,"company_type_th":"บริษัทจำกัด","submit_obj_big_type":"C","full_address":"49 หมู่ที่ 11 ต.จานใหญ่ อ.กันทรลักษ์ จ.ศรีสะเกษ","gov_fund_proj":null},{"financial":[{"year":"2564","income":1282757261.5699999332},{"year":"2563","income":866576292.4700000286},{"year":"2562","income":1330151298.5699999332},{"year":"2561","income":1039601875.4099999666}],"company_shareholder":{},"reg_date":"19\/03\/2553","company_name_th":"เอี่ยมอุบล จำกัด","company_id":"0335553000111","obj_tname":"การผลิตสตาร์ชมันสำปะหลัง","company_name_en":"EIAM UBON CO.,LTD.","tsic":10622,"cap_amt":580000000,"company_value":400470165,"company_type_th":"บริษัทจำกัด","submit_obj_big_type":"C","full_address":"199 หมู่ที่ 9  ต.โซง อ.น้ำยืน จ.อุบลราชธานี","gov_fund_proj":null},{"financial":[{"year":"2564","income":71841885.7300000042},{"year":"2563","income":54032342.950000003},{"year":"2562","income":52699377.1700000018},{"year":"2561","income":66305108.3299999982}],"company_shareholder":{},"reg_date":"11\/12\/2550","company_name_th":"เอี่ยมศิริ ไบโอ ก๊าซ จำกัด","company_id":"0275550000294","obj_tname":"การผลิตเชื้อเพลิงชีวภาพ","company_name_en":"EIAMSIRI  BIOGAS CO., LTD.","tsic":19202,"cap_amt":40000000,"company_value":60602973,"company_type_th":"บริษัทจำกัด","submit_obj_big_type":"C","full_address":"49\/1 หมู่ที่ 11  ต.จานใหญ่ อ.กันทรลักษ์ จ.ศรีสะเกษ","gov_fund_proj":null},{"financial":[{"year":"2564","income":7473742.1799999997},{"year":"2563","income":30852.82},{"year":"2562","income":1075958.1399999999},{"year":"2561","income":32914120.2100000009}],"company_shareholder":{},"reg_date":"26\/04\/2555","company_name_th":"อีบีพี อินเตอร์เทรด จำกัด","company_id":"0275555000209","obj_tname":"การขายส่งผลิตภัณฑ์อาหารอื่นๆซึ่งมิได้จัดประเภทไว้ในที่อื่น","company_name_en":"EBP INTERTRADE COMPANY LIMITED","tsic":46319,"cap_amt":40000000,"company_value":24881057,"company_type_th":"บริษัทจำกัด","submit_obj_big_type":"G","full_address":"98 หมู่ที่ 2  ต.หนองน้ำใส อ.วัฒนานคร จ.สระแก้ว","gov_fund_proj":null},{"financial":[{"year":"2564","income":34716275.8599999994},{"year":"2563","income":21405572.0500000007},{"year":"2562","income":20830032.0500000007},{"year":"2561","income":29538325.629999999}],"company_shareholder":{},"reg_date":"27\/09\/2549","company_name_th":"อีบีพี เอทานอล จำกัด","company_id":"0275549000219","obj_tname":"การผลิตมันเส้นและมันอัดเม็ด","company_name_en":"EBP ETHANOL COMPANY LIMITED","tsic":10621,"cap_amt":154000000,"company_value":177840308,"company_type_th":"บริษัทจำกัด","submit_obj_big_type":"C","full_address":"98 หมู่ที่ 2 ต.หนองน้ำใส อ.วัฒนานคร จ.สระแก้ว","gov_fund_proj":null},{"financial":[{"year":"2564","income":41547015.5900000036},{"year":"2563","income":27551482.2399999984},{"year":"2562","income":50180168.4900000021},{"year":"2561","income":34739211.8800000027}],"company_shareholder":{},"reg_date":"06\/09\/2553","company_name_th":"อียู ไบโอก๊าซ จำกัด","company_id":"0335553000235","obj_tname":"การผลิตก๊าซ","company_name_en":"E U BIOGAS CO.,LTD.","tsic":35201,"cap_amt":30000000,"company_value":105979583,"company_type_th":"บริษัทจำกัด","submit_obj_big_type":"D","full_address":"188 หมู่บ้านหนองอุดม หมู่ที่ 9  ต.โซง อ.น้ำยืน จ.อุบลราชธานี","gov_fund_proj":null},{"financial":[{"year":"2564","income":929594288.4700000286},{"year":"2563","income":677810095.0399999619},{"year":"2562","income":38620240.9699999988},{"year":"2561","income":12838.25}],"company_shareholder":{},"reg_date":"08\/03\/2559","company_name_th":"เอี่ยมอำนาจ แป้งมัน จำกัด","company_id":"0335559000113","obj_tname":"การผลิตสตาร์ชมันสำปะหลัง","company_name_en":"EIAM AM NAT TAPIOCA STARCH COMPANY LIMITED","tsic":10622,"cap_amt":315000000,"company_value":300396630,"company_type_th":"บริษัทจำกัด","submit_obj_big_type":"C","full_address":"199  หมู่ที่ 9 ต.โคกสาร อ.ชานุมาน จ.อำนาจเจริญ","gov_fund_proj":null},{"financial":[{"year":"2564","income":35586290.6799999997},{"year":"2563","income":5543280.4199999999},{"year":"2562","income":4502.21},{"year":"2561","income":2727.63}],"company_shareholder":{},"reg_date":"27\/04\/2559","company_name_th":"อีเอเอ็น ไบโอก๊าซ จำกัด","company_id":"0335559000237","obj_tname":"การผลิตก๊าซ","company_name_en":"EAN BIOGAS COMPANY LIMITED","tsic":35201,"cap_amt":54500000,"company_value":82261509,"company_type_th":"บริษัทจำกัด","submit_obj_big_type":"D","full_address":"199  หมู่ที่ 9 ต.โคกสาร อ.ชานุมาน จ.อำนาจเจริญ","gov_fund_proj":null},{"financial":[{"year":"2564","income":1124675521},{"year":"2563","income":875432524},{"year":"2562","income":956337186.5399999619},{"year":"2561","income":1161978109.2999999523}],"company_shareholder":{},"reg_date":"10\/02\/2543","company_name_th":"เอี่ยมบูรพา จำกัด","company_id":"0305543000208","obj_tname":"การผลิตสตาร์ชมันสำปะหลัง","company_name_en":"EARNEST HUGE CO., LTD.","tsic":10622,"cap_amt":500000000,"company_value":613957630,"company_type_th":"บริษัทจำกัด","submit_obj_big_type":"C","full_address":"98 หมู่ที่ 2 ต.หนองน้ำใส อ.วัฒนานคร จ.สระแก้ว","gov_fund_proj":null}]