[{"financial":[{"year":"2547","income":0},{"year":"2546","income":0},{"year":"2545","income":0},{"year":"2544","income":0}],"company_shareholder":{},"reg_date":"24\/02\/2543","company_name_th":"ณัฐโรจน์ จำกัด","company_id":"0105543019407","obj_tname":"ร้านขายปลีกคอมพิวเตอร์และอุปกรณ์ต่อพ่วงคอมพิวเตอร์","company_name_en":"NATHAROJ CO., LTD.","tsic":47411,"cap_amt":1000000,"company_value":0,"company_type_th":"บริษัทจำกัด","submit_obj_big_type":"G","full_address":"89 ซอยลาดพร้าว 80 (จันทิมา 6) ถนนลาดพร้าว แขวงวังทองหลาง เขตวังทองหลาง กรุงเทพมหานคร","gov_fund_proj":null}]