[{"financial":[{"year":"2564","income":0},{"year":"2563","income":0},{"year":"2562","income":0},{"year":"2561","income":0}],"company_shareholder":{},"reg_date":"20\/02\/2540","company_name_th":"หนองคายพิทยาภัณฑ์ จำกัด","company_id":"0105540018396","obj_tname":"-","company_name_en":"PLANT ENGINEERING AND CONSTRUCTION CO., LTD.","tsic":42101,"cap_amt":1000000,"company_value":0,"company_type_th":"บริษัทจำกัด","submit_obj_big_type":"F","full_address":"99 หมู่ที่ 3 ถนนโซ่พิสัย ต.โซ่ อ.โซ่พิสัย จ.บึงกาฬ","gov_fund_proj":null}]